dzonegit.py
dzonegit-0.15.dist-info/LICENSE
dzonegit-0.15.dist-info/METADATA
dzonegit-0.15.dist-info/WHEEL
dzonegit-0.15.dist-info/entry_points.txt
dzonegit-0.15.dist-info/top_level.txt
dzonegit-0.15.dist-info/RECORD
