Metadata-Version: 2.1
Name: dzonegit
Version: 0.15
Summary: Git hooks to manage a repository of DNS zones
Home-page: https://github.com/oskar456/dzonegit
Author: Ondřej Caletka
Author-email: ondrej@caletka.cz
License: MIT
Platform: UNKNOWN
Classifier: Development Status :: 4 - Beta
Classifier: Environment :: Console
Classifier: Intended Audience :: System Administrators
Classifier: License :: OSI Approved :: MIT License
Classifier: Operating System :: POSIX :: Linux
Classifier: Programming Language :: Python :: 3.5
Classifier: Programming Language :: Python :: 3.6
Classifier: Programming Language :: Python :: 3 :: Only
Classifier: Topic :: Software Development :: Version Control :: Git
Classifier: Topic :: System :: Systems Administration
Requires-Python: >=3.5
License-File: LICENSE
